LICENSE
README.md
setup.py
src/ask_me_something/__init__.py
src/ask_me_something/ask_me_something.py
src/ask_me_something.egg-info/PKG-INFO
src/ask_me_something.egg-info/SOURCES.txt
src/ask_me_something.egg-info/dependency_links.txt
src/ask_me_something.egg-info/entry_points.txt
src/ask_me_something.egg-info/not-zip-safe
src/ask_me_something.egg-info/requires.txt
src/ask_me_something.egg-info/top_level.txt