Metadata-Version: 2.1
Name: ask-me-something
Version: 0.1.0
Summary: A speak to text library.
Home-page: https://github.com/onuratakan/ask_me_something
Author: Onur Atakan ULUSOY
Author-email: atadogan06@gmail.com
License: MIT
Platform: UNKNOWN
Requires-Python: >= 3, < 3.7
License-File: LICENSE
